[
  {
    "name": "Tutorial",
    "relativeSite": [
      {
        "name": "w3schools",
        "url": "http://www.w3schools.com/css/default.asp"
      },
      {
        "name": "w3school",
        "url": "http://www.w3school.com.cn/css3/index.asp"
      },
      {
        "name": "MDN",
        "url": "https://developer.mozilla.org/en-US/docs/Web/CSS"
      }
    ]
  },
  {
    "name": "SASS",
    "relativeSite": [
      {
        "name": "SASS中文网",
        "url": "http://www.sasschina.com/guide/"
      },
      {
        "name": "SASS-W3CPlus",
        "url": "http://www.w3cplus.com/sassguide/"
      },
      {
        "name": "SASS-阮一峰",
        "url": "http://www.ruanyifeng.com/blog/2012/06/sass.html"
      }
    ]
  },
  {
    "name": "LESS",
    "relativeSite": [
      {
        "name": "Less中文网",
        "url": "http://lesscss.cn/"
      },
      {
        "name": "Less-W3CPlus",
        "url": "http://www.w3cplus.com/css/less"
      },
      {
        "name": "Less-RUNOOB",
        "url": "http://www.runoob.com/bootstrap/bootstrap-v2-less.html"
      }
    ]
  },
  {
    "name": "响应式布局",
    "relativeSite": [
      {
        "name": "maxdesign",
        "url": "http://maxdesign.com.au/css-layouts/"
      }
    ]
  }
]